{
	"configurations" : 
	[
		{
			"directories" : 
			[
				{
					"build" : ".",
					"hasInstallRule" : true,
					"minimumCMakeVersion" : 
					{
						"string" : "3.5"
					},
					"projectIndex" : 0,
					"source" : ".",
					"targetIndexes" : 
					[
						0,
						1
					]
				}
			],
			"name" : "",
			"projects" : 
			[
				{
					"directoryIndexes" : 
					[
						0
					],
					"name" : "smart_cane_slam",
					"targetIndexes" : 
					[
						0,
						1
					]
				}
			],
			"targets" : 
			[
				{
					"directoryIndex" : 0,
					"id" : "smart_cane_slam_uninstall::@6890427a1f51a3e7e1df",
					"jsonFile" : "target-smart_cane_slam_uninstall-6d16d0293cb9338ece05.json",
					"name" : "smart_cane_slam_uninstall",
					"projectIndex" : 0
				},
				{
					"directoryIndex" : 0,
					"id" : "uninstall::@6890427a1f51a3e7e1df",
					"jsonFile" : "target-uninstall-694a4403b6934228c495.json",
					"name" : "uninstall",
					"projectIndex" : 0
				}
			]
		}
	],
	"kind" : "codemodel",
	"paths" : 
	{
		"build" : "/home/daniel/smart_cane/build/smart_cane_slam",
		"source" : "/home/daniel/smart_cane/src/smart_cane_slam"
	},
	"version" : 
	{
		"major" : 2,
		"minor" : 0
	}
}
